gaussian_adaptive_attention/GaussianBlock.py
gaussian_adaptive_attention/__init__.py
gaussian_adaptive_attention-0.1.5.dist-info/LICENSE.md
gaussian_adaptive_attention-0.1.5.dist-info/METADATA
gaussian_adaptive_attention-0.1.5.dist-info/WHEEL
gaussian_adaptive_attention-0.1.5.dist-info/top_level.txt
gaussian_adaptive_attention-0.1.5.dist-info/RECORD
