Metadata-Version: 2.1
Name: gaussian-adaptive-attention
Version: 0.1.5
Summary: A Gaussian Adaptive Attention module for PyTorch
Home-page: https://github.com/yourusername/GaussianAdaptiveAttention
Author: Georgios Ioannides
Author-email: gioannid@alumni.cmu.edu
License: Apache 2.0
Platform: UNKNOWN
Classifier: License :: OSI Approved :: Apache Software License
Classifier: Programming Language :: Python :: 3
Classifier: Programming Language :: Python :: 3.7
Classifier: Programming Language :: Python :: 3.8
Classifier: Programming Language :: Python :: 3.9
License-File: LICENSE.md
Requires-Dist: torch
